limepy/__init__.py
limepy/dfspes.py
limepy/flowchart_rotation.txt
limepy/limepy.py
limepy/sample.py
limepy/sample2.py
limepy/sample3.py
limepy/spes.py
limepy/spes2.py
limepy/test.py
limepy/test2.py
limepy/test3.py
limepy/test_normalisation.py
limepy/test_sample.py
astro_limepy-1.2.1.dist-info/AUTHORS.rst
astro_limepy-1.2.1.dist-info/LICENSE
astro_limepy-1.2.1.dist-info/METADATA
astro_limepy-1.2.1.dist-info/WHEEL
astro_limepy-1.2.1.dist-info/top_level.txt
astro_limepy-1.2.1.dist-info/RECORD
