Metadata-Version: 2.2
Name: astro-limepy
Version: 1.2.1
Summary: Code to solve lowered isothermal model
Home-page: https://github.com/mgieles/limepy
Author: Mark Gieles, Alice Zocchi
Author-email: Mark Gieles <m.gieles@surrey.ac.uk>, Alice Zocchi <a.zocchi@surrey.ac.uk>
License: MIT License
Project-URL: documentation, https://limepy.readthedocs.org
Project-URL: repository, https://github.com/mgieles/limepy
Keywords: limepy
Classifier: Development Status :: 5 - Production/Stable
Classifier: Programming Language :: Python
Classifier: License :: OSI Approved :: MIT License
Classifier: Intended Audience :: Science/Research
Classifier: Topic :: Scientific/Engineering :: Astronomy
Requires-Python: >=3.8
License-File: LICENSE
License-File: AUTHORS.rst
Requires-Dist: numpy
Requires-Dist: scipy
Dynamic: author
Dynamic: home-page
